setup.py
aiopipes/__init__.py
aiopipes/filters.py
aiopipes/monitor.py
aiopipes/pipeio.py
aiopipes/pipeline.py
aiopipes/queue.py
aiopipes/runner.py
aiopipes/status.py
aiopipes/task.py
aiopipes.egg-info/PKG-INFO
aiopipes.egg-info/SOURCES.txt
aiopipes.egg-info/dependency_links.txt
aiopipes.egg-info/requires.txt
aiopipes.egg-info/top_level.txt
test/test_io.py
test/test_pipeline.py
test/test_runner.py