Metadata-Version: 1.0
Name: aiopipes
Version: 0.3.1
Summary: This module provides a set of pipe-like data structures for use with asyncio-based applications. See the GitHub repo for examples
Home-page: https://github.com/orf/aio-pipes
Author: Orf
Author-email: tom@tomforb.es
License: UNKNOWN
Platform: UNKNOWN
